<?xml version="1.0" encoding="UTF-8"?>
<Audio>
  <MediaId>5708</MediaId>
  <FileName>LIFECLEF2014_BIRDAMAZON_XC_WAV_RN5708.wav</FileName>
  <ClassId>pscjat</ClassId>
  <Date>2003-05-17</Date>
  <Time>11:40</Time>
  <Locality>Fazenda Nova, Brejo da Madre de Deus, Pernambuco</Locality>
  <Latitude>-8.140295</Latitude>
  <Longitude>-36.362858</Longitude>
  <Elevation>627</Elevation>
  <Author>Glauco Alves Pereira</Author>
  <AuthorID>ZWEROGGYVP</AuthorID>
  <Content>call</Content>
  <Comments>Open area</Comments>
  <Quality>2</Quality>
  <Year>BirdCLEF2014</Year>
  <BackgroundSpecies />
  <Order>Passeriformes</Order>
  <Family>Thraupidae</Family>
  <Genus>Sicalis</Genus>
  <Species>flaveola</Species>
  <Sub-species />
  <VernacularNames>Saffron Finch</VernacularNames>
</Audio>
