<?xml version="1.0" encoding="UTF-8"?>
<Audio>
  <MediaId>29430</MediaId>
  <FileName>LIFECLEF2015_BIRDAMAZON_XC_WAV_RN29430.wav</FileName>
  <ClassId>xeuhji</ClassId>
  <Date>2007-11-07</Date>
  <Time>14:00</Time>
  <Locality>Parque Regional Barbas-Bremen, Filandia, Quindio. Sector Bremen-La Popa</Locality>
  <Latitude>4.6717</Latitude>
  <Longitude>-75.6283</Longitude>
  <Elevation>1800</Elevation>
  <Author>Oscar Humberto Marin-Gomez</Author>
  <AuthorID>CSUHASNRSU</AuthorID>
  <Content>song</Content>
  <Comments>OHM 004B 0856. Tres individuos en rastrojo alto, forrajeando en arbustos bajos. Bosque montano bajo. 15m del Mic. Vocalización Natural. Cerca al campamento Bremenbird-seen:yesplayback-used:no</Comments>
  <Quality>1</Quality>
  <Year>BirdCLEF2015</Year>
  <BackgroundSpecies />
  <Order>Passeriformes</Order>
  <Family>Thraupidae</Family>
  <Genus>Tangara</Genus>
  <Species>vitriolina</Species>
  <Sub-species />
  <VernacularNames>Scrub Tanager</VernacularNames>
</Audio>
