<?xml version="1.0" encoding="UTF-8"?>
<Audio>
  <MediaId>12392</MediaId>
  <FileName>LIFECLEF2014_BIRDAMAZON_XC_WAV_RN12392.wav</FileName>
  <ClassId>afzbzd</ClassId>
  <Date>2013-10-05</Date>
  <Time>17:30</Time>
  <Locality>Campo Mourao, Paraná.</Locality>
  <Latitude>-24.0458</Latitude>
  <Longitude>-52.3828</Longitude>
  <Elevation>600</Elevation>
  <Author>Luiz C.  Silva</Author>
  <AuthorID>ORPKXJRFDZ</AuthorID>
  <Content>song</Content>
  <Comments>Duet song?bird-seen:yesplayback-used:no</Comments>
  <Quality>1</Quality>
  <Year>BirdCLEF2014</Year>
  <BackgroundSpecies />
  <Order>Cuculiformes</Order>
  <Family>Cuculidae</Family>
  <Genus>Tapera</Genus>
  <Species>naevia</Species>
  <Sub-species />
  <VernacularNames>Striped Cuckoo</VernacularNames>
</Audio>
