<?xml version="1.0" encoding="UTF-8"?>
<Audio>
  <MediaId>23781</MediaId>
  <FileName>LIFECLEF2015_BIRDAMAZON_XC_WAV_RN23781.wav</FileName>
  <ClassId>vdoulx</ClassId>
  <Date>2007-08-10</Date>
  <Time>10:15</Time>
  <Locality>Humedal de Cordoba, Bogota, Cundinamarca</Locality>
  <Latitude>NULL</Latitude>
  <Longitude>NULL</Longitude>
  <Elevation>2600</Elevation>
  <Author>Bernabe Lopez-Lanus</Author>
  <AuthorID>BYLLSJRVDZ</AuthorID>
  <Content>Call</Content>
  <Comments />
  <Quality>0</Quality>
  <Year>BirdCLEF2015</Year>
  <BackgroundSpecies />
  <Order>Passeriformes</Order>
  <Family>Icteridae</Family>
  <Genus>Icterus</Genus>
  <Species>nigrogularis</Species>
  <Sub-species />
  <VernacularNames>Yellow Oriole</VernacularNames>
</Audio>
