<?xml version="1.0" encoding="UTF-8"?>
<Audio>
  <MediaId>25777</MediaId>
  <FileName>LIFECLEF2015_BIRDAMAZON_XC_WAV_RN25777.wav</FileName>
  <ClassId>ayyyjw</ClassId>
  <Date>2011-04-10</Date>
  <Time>06:04</Time>
  <Locality>Gran Sabana, Bolívar</Locality>
  <Latitude>4.535</Latitude>
  <Longitude>-61.6218</Longitude>
  <Elevation>650</Elevation>
  <Author>Anthony Crease</Author>
  <AuthorID>ENEAFHQVOF</AuthorID>
  <Content>call, song</Content>
  <Comments>Seen singing from perches and advancing by short flights, in area of 1-2m high, spiny bushes, separated by cattle grazing, trees to 10m nearby, bright dry am, single call, then 3 trills, evidence of range extension, ssp? Recording made after playback.bird-seen:yesplayback-used:yes</Comments>
  <Quality>3</Quality>
  <Year>BirdCLEF2015</Year>
  <BackgroundSpecies>Leptotila rufaxilla,Crypturellus soui</BackgroundSpecies>
  <Order>Passeriformes</Order>
  <Family>Tyrannidae</Family>
  <Genus>Poecilotriccus</Genus>
  <Species>sylvia</Species>
  <Sub-species />
  <VernacularNames>Slaty-headed Tody-Flycatcher</VernacularNames>
</Audio>
