<?xml version="1.0" encoding="UTF-8"?>
<Audio>
  <MediaId>10482</MediaId>
  <FileName>LIFECLEF2014_BIRDAMAZON_XC_WAV_RN10482.wav</FileName>
  <ClassId>ibvnlg</ClassId>
  <Date>2007-11-15</Date>
  <Time>6:00</Time>
  <Locality>Nazaré, Bahia.</Locality>
  <Latitude>NULL</Latitude>
  <Longitude>NULL</Longitude>
  <Elevation>?</Elevation>
  <Author>Sidnei S. dos Santos</Author>
  <AuthorID>BHODJXTHGQ</AuthorID>
  <Content>Song</Content>
  <Comments />
  <Quality>1</Quality>
  <Year>BirdCLEF2014</Year>
  <BackgroundSpecies />
  <Order>Passeriformes</Order>
  <Family>Tyrannidae</Family>
  <Genus>Myiornis</Genus>
  <Species>auricularis</Species>
  <Sub-species />
  <VernacularNames>Eared Pygmy Tyrant</VernacularNames>
</Audio>
