<?xml version="1.0" encoding="UTF-8"?>
<Audio>
  <MediaId>31796</MediaId>
  <FileName>LIFECLEF2015_BIRDAMAZON_XC_WAV_RN31796.wav</FileName>
  <ClassId>wstxgv</ClassId>
  <Date>1999-09-14</Date>
  <Time>07:00</Time>
  <Locality>Reserva Extrativista Alto Juruá. Foz do Breu</Locality>
  <Latitude>-9.4123</Latitude>
  <Longitude>-72.7153</Longitude>
  <Elevation>250</Elevation>
  <Author>Jeremy Minns</Author>
  <AuthorID>DGVLLRYDXS</AuthorID>
  <Content>call, song</Content>
  <Comments>Low bushy vegetation between river and airstrip.</Comments>
  <Quality>0</Quality>
  <Year>BirdCLEF2015</Year>
  <BackgroundSpecies />
  <Order>Passeriformes</Order>
  <Family>Tyrannidae</Family>
  <Genus>Poecilotriccus</Genus>
  <Species>latirostris</Species>
  <Sub-species>latirostris</Sub-species>
  <VernacularNames>Rusty-fronted Tody-Flycatcher</VernacularNames>
</Audio>
