<?xml version="1.0" encoding="UTF-8"?>
<Audio>
  <MediaId>27505</MediaId>
  <FileName>LIFECLEF2015_BIRDAMAZON_XC_WAV_RN27505.wav</FileName>
  <ClassId>pswzyj</ClassId>
  <Date>2011-09-19</Date>
  <Time>?</Time>
  <Locality>Saint-Georges, piste de Saut Maripa</Locality>
  <Latitude>3.950143</Latitude>
  <Longitude>-51.794735</Longitude>
  <Elevation>50</Elevation>
  <Author>Alexandre Renaudier</Author>
  <AuthorID>GKADEITXTH</AuthorID>
  <Content>Song</Content>
  <Comments />
  <Quality>1</Quality>
  <Year>BirdCLEF2015</Year>
  <BackgroundSpecies>Myrmotherula brachyura,Ramphocelus carbo,Tyrannulus elatus</BackgroundSpecies>
  <Order>Passeriformes</Order>
  <Family>Vireonidae</Family>
  <Genus>Vireo</Genus>
  <Species>olivaceus</Species>
  <Sub-species />
  <VernacularNames>Red-eyed Vireo</VernacularNames>
</Audio>
