<?xml version="1.0" encoding="UTF-8"?>
<Audio>
  <MediaId>22930</MediaId>
  <FileName>LIFECLEF2015_BIRDAMAZON_XC_WAV_RN22930.wav</FileName>
  <ClassId>mnbzkx</ClassId>
  <Date>2006-10-13</Date>
  <Time>7:00</Time>
  <Locality>Manaus. ZF-2 road</Locality>
  <Latitude>-2.5501</Latitude>
  <Longitude>-60.0834</Longitude>
  <Elevation>?</Elevation>
  <Author>Thiago V. V. Costa</Author>
  <AuthorID>FPHQAPNAFU</AuthorID>
  <Content>song</Content>
  <Comments />
  <Quality>0</Quality>
  <Year>BirdCLEF2015</Year>
  <BackgroundSpecies>Trogon rufus</BackgroundSpecies>
  <Order>Trogoniformes</Order>
  <Family>Trogonidae</Family>
  <Genus>Pharomachrus</Genus>
  <Species>pavoninus</Species>
  <Sub-species>pavoninus</Sub-species>
  <VernacularNames>Pavonine Quetzal</VernacularNames>
</Audio>
