<?xml version="1.0" encoding="UTF-8"?>
<Audio>
  <MediaId>1365</MediaId>
  <FileName>LIFECLEF2014_BIRDAMAZON_XC_WAV_RN1365.wav</FileName>
  <ClassId>fmdsaj</ClassId>
  <Date>2010-12-13</Date>
  <Time>08:30</Time>
  <Locality>Floresta Nacional do Tapajós, Bacia 165, Santarem, Para</Locality>
  <Latitude>-2.7539</Latitude>
  <Longitude>-54.997</Longitude>
  <Elevation>?</Elevation>
  <Author>Alexander Lees</Author>
  <AuthorID>INDDBZAFJL</AuthorID>
  <Content>song</Content>
  <Comments>primary forest (once burnt)</Comments>
  <Quality>0</Quality>
  <Year>BirdCLEF2014</Year>
  <BackgroundSpecies>Xiphorhynchus guttatus,Myrmotherula sclateri,Cercomacra cinerascens,Tyranneutes stolzmanni,Chiroxiphia pareola,Lamprospiza melanoleuca,Saltator grossus</BackgroundSpecies>
  <Order>Passeriformes</Order>
  <Family>Tyrannidae</Family>
  <Genus>Piprites</Genus>
  <Species>chloris</Species>
  <Sub-species>tschudii</Sub-species>
  <VernacularNames>Wing-barred Piprites</VernacularNames>
</Audio>
