<?xml version="1.0" encoding="UTF-8"?>
<Audio>
  <MediaId>4122</MediaId>
  <FileName>LIFECLEF2014_BIRDAMAZON_XC_WAV_RN4122.wav</FileName>
  <ClassId>fqumzc</ClassId>
  <Date>2011-09-18</Date>
  <Time>06:14</Time>
  <Locality>Cristalino Jungle Lodge, MT</Locality>
  <Latitude>-9.5981</Latitude>
  <Longitude>-55.932</Longitude>
  <Elevation>260</Elevation>
  <Author>Eric DeFonso</Author>
  <AuthorID>KTLCZCRCQX</AuthorID>
  <Content>song</Content>
  <Comments>Quality improves toward the end. Habitat is terra firme forest.bird-seen:yesplayback-used:no</Comments>
  <Quality>2</Quality>
  <Year>BirdCLEF2014</Year>
  <BackgroundSpecies>Amazona kawalli,Saltator grossus,Leucopternis kuhli</BackgroundSpecies>
  <Order>Piciformes</Order>
  <Family>Picidae</Family>
  <Genus>Campephilus</Genus>
  <Species>melanoleucos</Species>
  <Sub-species />
  <VernacularNames>Crimson-crested Woodpecker</VernacularNames>
</Audio>
