<?xml version="1.0" encoding="UTF-8"?>
<Audio>
  <MediaId>497</MediaId>
  <FileName>LIFECLEF2014_BIRDAMAZON_XC_WAV_RN497.wav</FileName>
  <ClassId>nvlywx</ClassId>
  <Date>2008-09-08</Date>
  <Time>16:15</Time>
  <Locality>Pantanal Wildlife Center, MT</Locality>
  <Latitude>-16.7581</Latitude>
  <Longitude>-56.8764</Longitude>
  <Elevation>120</Elevation>
  <Author>Bradley Davis</Author>
  <AuthorID>YNXJLOESBB</AuthorID>
  <Content>song</Content>
  <Comments />
  <Quality>1</Quality>
  <Year>BirdCLEF2014</Year>
  <BackgroundSpecies>Leptotila verreauxi,Antilophia galeata,Crypturellus undulatus</BackgroundSpecies>
  <Order>Passeriformes</Order>
  <Family>Thamnophilidae</Family>
  <Genus>Cercomacra</Genus>
  <Species>melanaria</Species>
  <Sub-species />
  <VernacularNames>Mato Grosso Antbird</VernacularNames>
</Audio>
