<?xml version="1.0" encoding="UTF-8"?>
<Audio>
  <MediaId>23860</MediaId>
  <FileName>LIFECLEF2015_BIRDAMAZON_XC_WAV_RN23860.wav</FileName>
  <ClassId>iofesp</ClassId>
  <Date>2004-08-13</Date>
  <Time>10:41</Time>
  <Locality>Borba, Amazonas</Locality>
  <Latitude>-4.388175</Latitude>
  <Longitude>-59.593406</Longitude>
  <Elevation>30</Elevation>
  <Author>Jeremy Minns</Author>
  <AuthorID>DGVLLRYDXS</AuthorID>
  <Content>Song</Content>
  <Comments>Terra firme forest.</Comments>
  <Quality>3</Quality>
  <Year>BirdCLEF2015</Year>
  <BackgroundSpecies />
  <Order>Passeriformes</Order>
  <Family>Tyrannidae</Family>
  <Genus>Rhynchocyclus</Genus>
  <Species>olivaceus</Species>
  <Sub-species>sordidus</Sub-species>
  <VernacularNames>Olivaceous Flatbill</VernacularNames>
</Audio>
