<?xml version="1.0" encoding="UTF-8"?>
<Audio>
  <MediaId>2669</MediaId>
  <FileName>LIFECLEF2014_BIRDAMAZON_XC_WAV_RN2669.wav</FileName>
  <ClassId>fakmli</ClassId>
  <Date>2005-11-20</Date>
  <Time>6:05</Time>
  <Locality>Parque do Zizo, Sao Paulo State</Locality>
  <Latitude>-24.017146</Latitude>
  <Longitude>-47.81044</Longitude>
  <Elevation>630</Elevation>
  <Author>Bob Planqué</Author>
  <AuthorID>OH38YHKJBS</AuthorID>
  <Content>dawn song</Content>
  <Comments>from bamboo thicket</Comments>
  <Quality>2</Quality>
  <Year>BirdCLEF2014</Year>
  <BackgroundSpecies>Schiffornis virescens,Habia rubica,Pyriglena leucoptera,Anabazenops fuscus</BackgroundSpecies>
  <Order>Passeriformes</Order>
  <Family>Tyrannidae</Family>
  <Genus>Platyrinchus</Genus>
  <Species>mystaceus</Species>
  <Sub-species />
  <VernacularNames>White-throated Spadebill</VernacularNames>
</Audio>
