<?xml version="1.0" encoding="UTF-8"?>
<Audio>
  <MediaId>30503</MediaId>
  <FileName>LIFECLEF2015_BIRDAMAZON_XC_WAV_RN30503.wav</FileName>
  <ClassId>tmmseh</ClassId>
  <Date>2013-06-22</Date>
  <Time>11:30</Time>
  <Locality>Xapuri, Acre</Locality>
  <Latitude>-10.7427</Latitude>
  <Longitude>-68.2818</Longitude>
  <Elevation>220</Elevation>
  <Author>Marcos A. Melo</Author>
  <AuthorID>MRGDYNJGUJ</AuthorID>
  <Content>alarm call</Content>
  <Comments>bird-seen:yesplayback-used:no</Comments>
  <Quality>1</Quality>
  <Year>BirdCLEF2015</Year>
  <BackgroundSpecies>Hemitriccus iohannis</BackgroundSpecies>
  <Order>Opisthocomiformes</Order>
  <Family>Opisthocomidae</Family>
  <Genus>Opisthocomus</Genus>
  <Species>hoazin</Species>
  <Sub-species />
  <VernacularNames>Hoatzin</VernacularNames>
</Audio>
