<?xml version="1.0" encoding="UTF-8"?>
<Audio>
  <MediaId>31279</MediaId>
  <FileName>LIFECLEF2015_BIRDAMAZON_XC_WAV_RN31279.wav</FileName>
  <ClassId>uqcfuk</ClassId>
  <Date>2010-10-11</Date>
  <Time>18:36</Time>
  <Locality>Puerto Lopez, Rio Humea (meta)</Locality>
  <Latitude>4.1551</Latitude>
  <Longitude>-72.9228</Longitude>
  <Elevation>100</Elevation>
  <Author>Oswaldo Cortes</Author>
  <AuthorID>VVDRVZCVWW</AuthorID>
  <Content>call</Content>
  <Comments />
  <Quality>3</Quality>
  <Year>BirdCLEF2015</Year>
  <BackgroundSpecies />
  <Order>Caprimulgiformes</Order>
  <Family>Caprimulgidae</Family>
  <Genus>Antrostomus</Genus>
  <Species>rufus</Species>
  <Sub-species />
  <VernacularNames>Rufous Nightjar</VernacularNames>
</Audio>
