<?xml version="1.0" encoding="UTF-8"?>
<Audio>
  <MediaId>23741</MediaId>
  <FileName>LIFECLEF2015_BIRDAMAZON_XC_WAV_RN23741.wav</FileName>
  <ClassId>bpyrxb</ClassId>
  <Date>2011-10-04</Date>
  <Time>?</Time>
  <Locality>Maripasoula, Grand Inini</Locality>
  <Latitude>NULL</Latitude>
  <Longitude>NULL</Longitude>
  <Elevation>90</Elevation>
  <Author>Alexandre Renaudier</Author>
  <AuthorID>GKADEITXTH</AuthorID>
  <Content>?</Content>
  <Comments />
  <Quality>2</Quality>
  <Year>BirdCLEF2015</Year>
  <BackgroundSpecies>Atticora fasciata,Rhytipterna simplex</BackgroundSpecies>
  <Order>Passeriformes</Order>
  <Family>Tyrannidae</Family>
  <Genus>Myiornis</Genus>
  <Species>ecaudatus</Species>
  <Sub-species />
  <VernacularNames>Short-tailed Pygmy Tyrant</VernacularNames>
</Audio>
