<?xml version="1.0" encoding="UTF-8"?>
<Audio>
  <MediaId>10820</MediaId>
  <FileName>LIFECLEF2014_BIRDAMAZON_XC_WAV_RN10820.wav</FileName>
  <ClassId>inyngh</ClassId>
  <Date>1996-07-25</Date>
  <Time>12:35</Time>
  <Locality>Ubatuba, SP. Praia Vermelha do Sul.</Locality>
  <Latitude>-23.5167</Latitude>
  <Longitude>-45.1667</Longitude>
  <Elevation>5</Elevation>
  <Author>Jeremy Minns</Author>
  <AuthorID>DGVLLRYDXS</AuthorID>
  <Content>call</Content>
  <Comments>In garden in a well wooded condominium beside the sea. Male.</Comments>
  <Quality>3</Quality>
  <Year>BirdCLEF2014</Year>
  <BackgroundSpecies>Coereba flaveola</BackgroundSpecies>
  <Order>Passeriformes</Order>
  <Family>Thraupidae</Family>
  <Genus>Tachyphonus</Genus>
  <Species>coronatus</Species>
  <Sub-species />
  <VernacularNames>Ruby-crowned Tanager</VernacularNames>
</Audio>
