<?xml version="1.0" encoding="UTF-8"?>
<Audio>
  <MediaId>11493</MediaId>
  <FileName>LIFECLEF2014_BIRDAMAZON_XC_WAV_RN11493.wav</FileName>
  <ClassId>uuvfxv</ClassId>
  <Date>2013-02-05</Date>
  <Time>08:22</Time>
  <Locality>left bank of Rio Uraricuera, just east of BR-174, Roraima</Locality>
  <Latitude>3.473</Latitude>
  <Longitude>-60.8972</Longitude>
  <Elevation>80</Elevation>
  <Author>Jon King</Author>
  <AuthorID>LNEEOOWCQR</AuthorID>
  <Content>call, song</Content>
  <Comments>Distance to mic. 6m. Natural calls and one song phrase (at 0.25) given from ground, calls in contact with another individual c.20m away. Open understory of dry seasonally flooded dense thorny gallery forest. Some literature suggests this species does not occur in this region of Brasil.bird-seen:yesplayback-used:no</Comments>
  <Quality>1</Quality>
  <Year>BirdCLEF2014</Year>
  <BackgroundSpecies />
  <Order>Passeriformes</Order>
  <Family>Parulidae</Family>
  <Genus>Myiothlypis</Genus>
  <Species>flaveola</Species>
  <Sub-species />
  <VernacularNames>Flavescent Warbler</VernacularNames>
</Audio>
