<?xml version="1.0" encoding="UTF-8"?>
<Audio>
  <MediaId>19702</MediaId>
  <FileName>LIFECLEF2015_BIRDAMAZON_XC_WAV_RN19702.wav</FileName>
  <ClassId>swkumm</ClassId>
  <Date>2000-05-31</Date>
  <Time>am</Time>
  <Locality>Veredas Cayapal/Buenavista/Anatoli (Puerto Lleras-Cachipay), La Mesa, Cundinamarca</Locality>
  <Latitude>NULL</Latitude>
  <Longitude>NULL</Longitude>
  <Elevation>1650</Elevation>
  <Author>Bernabe Lopez-Lanus</Author>
  <AuthorID>BYLLSJRVDZ</AuthorID>
  <Content>Song</Content>
  <Comments />
  <Quality>1</Quality>
  <Year>BirdCLEF2015</Year>
  <BackgroundSpecies />
  <Order>Passeriformes</Order>
  <Family>Thraupidae</Family>
  <Genus>Rhodinocichla</Genus>
  <Species>rosea</Species>
  <Sub-species />
  <VernacularNames>Rosy Thrush-Tanager</VernacularNames>
</Audio>
