<?xml version="1.0" encoding="UTF-8"?>
<Audio>
  <MediaId>1369</MediaId>
  <FileName>LIFECLEF2014_BIRDAMAZON_XC_WAV_RN1369.wav</FileName>
  <ClassId>ppearp</ClassId>
  <Date>2007-11-14</Date>
  <Time>10:00</Time>
  <Locality>APA de Grumari - RJ</Locality>
  <Latitude>-23.0917</Latitude>
  <Longitude>-43.5584</Longitude>
  <Elevation>15</Elevation>
  <Author>Ricardo Gagliardi</Author>
  <AuthorID>YRDADNREOP</AuthorID>
  <Content>call</Content>
  <Comments />
  <Quality>2</Quality>
  <Year>BirdCLEF2014</Year>
  <BackgroundSpecies />
  <Order>Passeriformes</Order>
  <Family>Tyrannidae</Family>
  <Genus>Tolmomyias</Genus>
  <Species>flaviventris</Species>
  <Sub-species>flaviventris</Sub-species>
  <VernacularNames>Ochre-lored Flatbill</VernacularNames>
</Audio>
