<?xml version="1.0" encoding="UTF-8"?>
<Audio>
  <MediaId>30073</MediaId>
  <FileName>LIFECLEF2015_BIRDAMAZON_XC_WAV_RN30073.wav</FileName>
  <ClassId>ryckte</ClassId>
  <Date>2014-01-10</Date>
  <Time>16:30</Time>
  <Locality>Reserva Natural Salto Morato, Guaraqueçaba, Paraná</Locality>
  <Latitude>-25.182</Latitude>
  <Longitude>-48.2981</Longitude>
  <Elevation>30</Elevation>
  <Author>João Antônio de B. Vitto</Author>
  <AuthorID>RIVNLYTULO</AuthorID>
  <Content>song</Content>
  <Comments>bird-seen:yesplayback-used:yes</Comments>
  <Quality>0</Quality>
  <Year>BirdCLEF2015</Year>
  <BackgroundSpecies />
  <Order>Passeriformes</Order>
  <Family>Thamnophilidae</Family>
  <Genus>Drymophila</Genus>
  <Species>squamata</Species>
  <Sub-species />
  <VernacularNames>Scaled Antbird</VernacularNames>
</Audio>
