<?xml version="1.0" encoding="UTF-8"?>
<Audio>
  <MediaId>14381</MediaId>
  <FileName>LIFECLEF2015_BIRDAMAZON_XC_WAV_RN14381.wav</FileName>
  <ClassId>vfxhsh</ClassId>
  <Date>2002-11-06</Date>
  <Time>07:39:59</Time>
  <Locality>Ecoparque Los Besotes, Valledupar, Cesar</Locality>
  <Latitude>10.57525</Latitude>
  <Longitude>-73.31055</Longitude>
  <Elevation>500</Elevation>
  <Author>Sergio Córdoba Córdoba (Colección de Sonidos Ambientales - Instituto Humboldt)</Author>
  <AuthorID>XMFDPACYJN</AuthorID>
  <Content>song</Content>
  <Comments>BSA 11828To obtain a wav file of the original recording, please contact csa@humboldt.org.coplayback-used:no</Comments>
  <Quality>2</Quality>
  <Year>BirdCLEF2015</Year>
  <BackgroundSpecies>Icterus chrysater</BackgroundSpecies>
  <Order>Apodiformes</Order>
  <Family>Trochilidae</Family>
  <Genus>Chlorostilbon</Genus>
  <Species>gibsoni</Species>
  <Sub-species />
  <VernacularNames>Red-billed Emerald</VernacularNames>
</Audio>
