<?xml version="1.0" encoding="UTF-8"?>
<Audio>
  <MediaId>23899</MediaId>
  <FileName>LIFECLEF2015_BIRDAMAZON_XC_WAV_RN23899.wav</FileName>
  <ClassId>tlnmxr</ClassId>
  <Date>2007-12-02</Date>
  <Time>11:15</Time>
  <Locality>Parque Regional Barbas-Bremen, Filandia, Quindio. Sector Bremen-La Popa</Locality>
  <Latitude>4.6717</Latitude>
  <Longitude>-75.6283</Longitude>
  <Elevation>1900</Elevation>
  <Author>Oscar Humberto Marin-Gomez</Author>
  <AuthorID>CSUHASNRSU</AuthorID>
  <Content>song</Content>
  <Comments>Ref: OHM12B 0510bird-seen:noplayback-used:no</Comments>
  <Quality>2</Quality>
  <Year>BirdCLEF2015</Year>
  <BackgroundSpecies />
  <Order>Passeriformes</Order>
  <Family>Furnariidae</Family>
  <Genus>Syndactyla</Genus>
  <Species>subalaris</Species>
  <Sub-species />
  <VernacularNames>Lineated Foliage-gleaner</VernacularNames>
</Audio>
