<?xml version="1.0" encoding="UTF-8"?>
<Audio>
  <MediaId>25727</MediaId>
  <FileName>LIFECLEF2015_BIRDAMAZON_XC_WAV_RN25727.wav</FileName>
  <ClassId>jslgyy</ClassId>
  <Date>1997-10-05</Date>
  <Time>00:00</Time>
  <Locality>near Honda, central Magdalena valley, Tolima</Locality>
  <Latitude>NULL</Latitude>
  <Longitude>NULL</Longitude>
  <Elevation>?</Elevation>
  <Author>Todd Mark</Author>
  <AuthorID>CLKPHLYUHA</AuthorID>
  <Content>?</Content>
  <Comments />
  <Quality>2</Quality>
  <Year>BirdCLEF2015</Year>
  <BackgroundSpecies />
  <Order>Passeriformes</Order>
  <Family>Pipridae</Family>
  <Genus>Machaeropterus</Genus>
  <Species>striolatus</Species>
  <Sub-species>antioquiae</Sub-species>
  <VernacularNames>Western Striped Manakin</VernacularNames>
</Audio>
