<?xml version="1.0" encoding="UTF-8"?>
<Audio>
  <MediaId>14926</MediaId>
  <FileName>LIFECLEF2015_BIRDAMAZON_XC_WAV_RN14926.wav</FileName>
  <ClassId>xrkpcj</ClassId>
  <Date>2008-01-26</Date>
  <Time>13:05</Time>
  <Locality>Hato Pinero, Bosque Mataje, Cojedes</Locality>
  <Latitude>8.9</Latitude>
  <Longitude>-68.027</Longitude>
  <Elevation>70</Elevation>
  <Author>Daniel Lane</Author>
  <AuthorID>WOEAFQRMUD</AuthorID>
  <Content>call</Content>
  <Comments>Two males sitting between 4-8m up. Responding to playback.</Comments>
  <Quality>1</Quality>
  <Year>BirdCLEF2015</Year>
  <BackgroundSpecies>Amazona ochrocephala</BackgroundSpecies>
  <Order>Passeriformes</Order>
  <Family>Pipridae</Family>
  <Genus>Chiroxiphia</Genus>
  <Species>lanceolata</Species>
  <Sub-species />
  <VernacularNames>Lance-tailed Manakin</VernacularNames>
</Audio>
