<?xml version="1.0" encoding="UTF-8"?>
<Audio>
  <MediaId>299</MediaId>
  <FileName>LIFECLEF2014_BIRDAMAZON_XC_WAV_RN299.wav</FileName>
  <ClassId>czvsyl</ClassId>
  <Date>2007-06-27</Date>
  <Time>14:40</Time>
  <Locality>Reserva Ecológica de Guapiaçu, RJ</Locality>
  <Latitude>-22.5001</Latitude>
  <Longitude>-42.7167</Longitude>
  <Elevation>?</Elevation>
  <Author>Leonardo Pimentel</Author>
  <AuthorID>JHBOHGJALL</AuthorID>
  <Content>Song</Content>
  <Comments />
  <Quality>1</Quality>
  <Year>BirdCLEF2014</Year>
  <BackgroundSpecies>Terenura maculata,Chiroxiphia caudata</BackgroundSpecies>
  <Order>Passeriformes</Order>
  <Family>Thamnophilidae</Family>
  <Genus>Myrmotherula</Genus>
  <Species>unicolor</Species>
  <Sub-species />
  <VernacularNames>Unicolored Antwren</VernacularNames>
</Audio>
