<?xml version="1.0" encoding="UTF-8"?>
<Audio>
  <MediaId>939</MediaId>
  <FileName>LIFECLEF2014_BIRDAMAZON_XC_WAV_RN939.wav</FileName>
  <ClassId>fakmli</ClassId>
  <Date>2012-04-01</Date>
  <Time>13:09</Time>
  <Locality>Timbaúba, Pernambuco</Locality>
  <Latitude>-7.6096</Latitude>
  <Longitude>-35.3952</Longitude>
  <Elevation>440</Elevation>
  <Author>Marcus Braun</Author>
  <AuthorID>EICLYDGEKS</AuthorID>
  <Content>song</Content>
  <Comments>99% certainty (bird not seen)bird-seen:noplayback-used:no</Comments>
  <Quality>5</Quality>
  <Year>BirdCLEF2014</Year>
  <BackgroundSpecies>Manacus manacus</BackgroundSpecies>
  <Order>Passeriformes</Order>
  <Family>Tyrannidae</Family>
  <Genus>Platyrinchus</Genus>
  <Species>mystaceus</Species>
  <Sub-species />
  <VernacularNames>White-throated Spadebill</VernacularNames>
</Audio>
