<?xml version="1.0" encoding="UTF-8"?>
<Audio>
  <MediaId>4507</MediaId>
  <FileName>LIFECLEF2014_BIRDAMAZON_XC_WAV_RN4507.wav</FileName>
  <ClassId>rfdfsw</ClassId>
  <Date>1999-03-01</Date>
  <Time>08:30</Time>
  <Locality>Perequê - Angra dos Reis - RJ</Locality>
  <Latitude>-23.012</Latitude>
  <Longitude>-44.5351</Longitude>
  <Elevation>50</Elevation>
  <Author>Jeremy Minns</Author>
  <AuthorID>DGVLLRYDXS</AuthorID>
  <Content>Song</Content>
  <Comments>Overgrown banana plantation near humid forest.</Comments>
  <Quality>2</Quality>
  <Year>BirdCLEF2014</Year>
  <BackgroundSpecies>Formicivora erythronotos</BackgroundSpecies>
  <Order>Passeriformes</Order>
  <Family>Vireonidae</Family>
  <Genus>Hylophilus</Genus>
  <Species>thoracicus</Species>
  <Sub-species>thoracicus</Sub-species>
  <VernacularNames>Lemon-chested Greenlet</VernacularNames>
</Audio>
