<?xml version="1.0" encoding="UTF-8"?>
<Audio>
  <MediaId>614</MediaId>
  <FileName>LIFECLEF2014_BIRDAMAZON_XC_WAV_RN614.wav</FileName>
  <ClassId>rlqpij</ClassId>
  <Date>2010-09-29</Date>
  <Time>09:00</Time>
  <Locality>São José dos Campos</Locality>
  <Latitude>NULL</Latitude>
  <Longitude>NULL</Longitude>
  <Elevation>650</Elevation>
  <Author>Rodrigo Dela Rosa</Author>
  <AuthorID>VGXDJMKETZ</AuthorID>
  <Content>Call</Content>
  <Comments />
  <Quality>2</Quality>
  <Year>BirdCLEF2014</Year>
  <BackgroundSpecies>Legatus leucophaius</BackgroundSpecies>
  <Order>Passeriformes</Order>
  <Family>Tyrannidae</Family>
  <Genus>Myiodynastes</Genus>
  <Species>maculatus</Species>
  <Sub-species />
  <VernacularNames>Streaked Flycatcher</VernacularNames>
</Audio>
