<?xml version="1.0" encoding="UTF-8"?>
<Audio>
  <MediaId>28892</MediaId>
  <FileName>LIFECLEF2015_BIRDAMAZON_XC_WAV_RN28892.wav</FileName>
  <ClassId>mzajou</ClassId>
  <Date>2010-10-29</Date>
  <Time>08:00</Time>
  <Locality>Alto Anchicaya, corregimiento El Danubio, Valle</Locality>
  <Latitude>3.389</Latitude>
  <Longitude>-76.8</Longitude>
  <Elevation>435</Elevation>
  <Author>Karolina Fierro-Calderon</Author>
  <AuthorID>MGJDNXGRDQ</AuthorID>
  <Content>song</Content>
  <Comments />
  <Quality>3</Quality>
  <Year>BirdCLEF2015</Year>
  <BackgroundSpecies />
  <Order>Passeriformes</Order>
  <Family>Cardinalidae</Family>
  <Genus>Saltator</Genus>
  <Species>grossus</Species>
  <Sub-species />
  <VernacularNames>Slate-colored Grosbeak</VernacularNames>
</Audio>
