<?xml version="1.0" encoding="UTF-8"?>
<Audio>
  <MediaId>16605</MediaId>
  <FileName>LIFECLEF2015_BIRDAMAZON_XC_WAV_RN16605.wav</FileName>
  <ClassId>qldqit</ClassId>
  <Date>2013-11-13</Date>
  <Time>18:30</Time>
  <Locality>Córrego do Engano, Miracatu São Paulo</Locality>
  <Latitude>NULL</Latitude>
  <Longitude>NULL</Longitude>
  <Elevation>650</Elevation>
  <Author>Dante Buzzetti</Author>
  <AuthorID>YOXWKYFZAP</AuthorID>
  <Content>song</Content>
  <Comments>bird-seen:noplayback-used:no</Comments>
  <Quality>0</Quality>
  <Year>BirdCLEF2015</Year>
  <BackgroundSpecies>Turdus albicollis</BackgroundSpecies>
  <Order>Passeriformes</Order>
  <Family>Furnariidae</Family>
  <Genus>Philydor</Genus>
  <Species>atricapillus</Species>
  <Sub-species />
  <VernacularNames>Black-capped Foliage-gleaner</VernacularNames>
</Audio>
