<?xml version="1.0" encoding="UTF-8"?>
<Audio>
  <MediaId>25453</MediaId>
  <FileName>LIFECLEF2015_BIRDAMAZON_XC_WAV_RN25453.wav</FileName>
  <ClassId>ffvgyk</ClassId>
  <Date>2007-01-00</Date>
  <Time>xx:xx</Time>
  <Locality>La Lana, San Pedro de los Milagros, Antioquia</Locality>
  <Latitude>6.4495</Latitude>
  <Longitude>-75.5942</Longitude>
  <Elevation>2700</Elevation>
  <Author>Thomas Donegan</Author>
  <AuthorID>OXSIOLJJUP</AuthorID>
  <Content>Song</Content>
  <Comments />
  <Quality>3</Quality>
  <Year>BirdCLEF2015</Year>
  <BackgroundSpecies>Synallaxis azarae,Myiothlypis coronata</BackgroundSpecies>
  <Order>Passeriformes</Order>
  <Family>Troglodytidae</Family>
  <Genus>Henicorhina</Genus>
  <Species>leucophrys</Species>
  <Sub-species />
  <VernacularNames>Grey-breasted Wood Wren</VernacularNames>
</Audio>
