<?xml version="1.0" encoding="UTF-8"?>
<Audio>
  <MediaId>17832</MediaId>
  <FileName>LIFECLEF2015_BIRDAMAZON_XC_WAV_RN17832.wav</FileName>
  <ClassId>cpigyt</ClassId>
  <Date>1998-06-10</Date>
  <Time>07:21</Time>
  <Locality>Finca La Carbonera (canon del rio Toche), Tolima</Locality>
  <Latitude>NULL</Latitude>
  <Longitude>NULL</Longitude>
  <Elevation>2800</Elevation>
  <Author>Bernabe Lopez-Lanus</Author>
  <AuthorID>BYLLSJRVDZ</AuthorID>
  <Content>Call</Content>
  <Comments />
  <Quality>0</Quality>
  <Year>BirdCLEF2015</Year>
  <BackgroundSpecies />
  <Order>Piciformes</Order>
  <Family>Ramphastidae</Family>
  <Genus>Andigena</Genus>
  <Species>nigrirostris</Species>
  <Sub-species>spilorhynchus</Sub-species>
  <VernacularNames>Black-billed Mountain Toucan</VernacularNames>
</Audio>
