<?xml version="1.0" encoding="UTF-8"?>
<Audio>
  <MediaId>12228</MediaId>
  <FileName>LIFECLEF2014_BIRDAMAZON_XC_WAV_RN12228.wav</FileName>
  <ClassId>bnpmye</ClassId>
  <Date>2008-11-02</Date>
  <Time>12:00</Time>
  <Locality>Km 04 - Laurentino - Santa Catarina</Locality>
  <Latitude>-27.2176</Latitude>
  <Longitude>-49.7173</Longitude>
  <Elevation>350</Elevation>
  <Author>www.aapimentao.com.br</Author>
  <AuthorID>VVQBELMRMH</AuthorID>
  <Content>?</Content>
  <Comments />
  <Quality>0</Quality>
  <Year>BirdCLEF2014</Year>
  <BackgroundSpecies />
  <Order>Charadriiformes</Order>
  <Family>Jacanidae</Family>
  <Genus>Jacana</Genus>
  <Species>jacana</Species>
  <Sub-species />
  <VernacularNames>Wattled Jacana</VernacularNames>
</Audio>
