<?xml version="1.0" encoding="UTF-8"?>
<Audio>
  <MediaId>3186</MediaId>
  <FileName>LIFECLEF2014_BIRDAMAZON_XC_WAV_RN3186.wav</FileName>
  <ClassId>wckepf</ClassId>
  <Date>2006-08-26</Date>
  <Time>16:30</Time>
  <Locality>Parque Nacional do Catimbau, Buíque, state of Pernambuco</Locality>
  <Latitude>-8.585095</Latitude>
  <Longitude>-37.20932</Longitude>
  <Elevation>800</Elevation>
  <Author>Mauricio Cabral Periquito</Author>
  <AuthorID>HERKCTHDZI</AuthorID>
  <Content>call</Content>
  <Comments />
  <Quality>3</Quality>
  <Year>BirdCLEF2014</Year>
  <BackgroundSpecies />
  <Order>Passeriformes</Order>
  <Family>Tyrannidae</Family>
  <Genus>Euscarthmus</Genus>
  <Species>meloryphus</Species>
  <Sub-species />
  <VernacularNames>Tawny-crowned Pygmy Tyrant</VernacularNames>
</Audio>
