<?xml version="1.0" encoding="UTF-8"?>
<Audio>
  <MediaId>31754</MediaId>
  <FileName>LIFECLEF2015_BIRDAMAZON_XC_WAV_RN31754.wav</FileName>
  <ClassId>pzlpoj</ClassId>
  <Date>2011-10-07</Date>
  <Time>?</Time>
  <Locality>Maripasoula, Grand Inini</Locality>
  <Latitude>NULL</Latitude>
  <Longitude>NULL</Longitude>
  <Elevation>90</Elevation>
  <Author>Alexandre Renaudier</Author>
  <AuthorID>GKADEITXTH</AuthorID>
  <Content>Song</Content>
  <Comments>early morning....</Comments>
  <Quality>2</Quality>
  <Year>BirdCLEF2015</Year>
  <BackgroundSpecies>Myrmotherula menetriesii,Tyranneutes virescens,Patagioenas plumbea,Cercomacra cinerascens</BackgroundSpecies>
  <Order>Passeriformes</Order>
  <Family>Furnariidae</Family>
  <Genus>Xenops</Genus>
  <Species>minutus</Species>
  <Sub-species />
  <VernacularNames>Plain Xenops</VernacularNames>
</Audio>
