<?xml version="1.0" encoding="UTF-8"?>
<Audio>
  <MediaId>22268</MediaId>
  <FileName>LIFECLEF2015_BIRDAMAZON_XC_WAV_RN22268.wav</FileName>
  <ClassId>fdjofa</ClassId>
  <Date>2006-12-30</Date>
  <Time>06:15</Time>
  <Locality>road to the Rio Cuyuni east of Tumeremo, Bolivar</Locality>
  <Latitude>6.9001</Latitude>
  <Longitude>-61.2501</Longitude>
  <Elevation>200</Elevation>
  <Author>Andrew Spencer</Author>
  <AuthorID>CDTGHVBGZP</AuthorID>
  <Content>flight call</Content>
  <Comments />
  <Quality>1</Quality>
  <Year>BirdCLEF2015</Year>
  <BackgroundSpecies />
  <Order>Psittaciformes</Order>
  <Family>Psittacidae</Family>
  <Genus>Pionus</Genus>
  <Species>menstruus</Species>
  <Sub-species />
  <VernacularNames>Blue-headed Parrot</VernacularNames>
</Audio>
