<?xml version="1.0" encoding="UTF-8"?>
<Audio>
  <MediaId>20563</MediaId>
  <FileName>LIFECLEF2015_BIRDAMAZON_XC_WAV_RN20563.wav</FileName>
  <ClassId>xpclwf</ClassId>
  <Date>2006-08-06</Date>
  <Time>9:10</Time>
  <Locality>Iracema Falls, Presidente Figuereido, AM</Locality>
  <Latitude>-1.9798</Latitude>
  <Longitude>-60.0509</Longitude>
  <Elevation>130</Elevation>
  <Author>Rolf A. de By</Author>
  <AuthorID>PTYTXQRLSZ</AuthorID>
  <Content>song</Content>
  <Comments />
  <Quality>2</Quality>
  <Year>BirdCLEF2015</Year>
  <BackgroundSpecies>Vireo olivaceus</BackgroundSpecies>
  <Order>Passeriformes</Order>
  <Family>Icteridae</Family>
  <Genus>Icterus</Genus>
  <Species>cayanensis</Species>
  <Sub-species>chrysocephalus</Sub-species>
  <VernacularNames>Epaulet Oriole</VernacularNames>
</Audio>
