<?xml version="1.0" encoding="UTF-8"?>
<Audio>
  <MediaId>788</MediaId>
  <FileName>LIFECLEF2014_BIRDAMAZON_XC_WAV_RN788.wav</FileName>
  <ClassId>jocatj</ClassId>
  <Date>2006-01-19</Date>
  <Time>10:15</Time>
  <Locality>Serra dos Carajás, PA</Locality>
  <Latitude>-6.1603</Latitude>
  <Longitude>-50.3459</Longitude>
  <Elevation>230</Elevation>
  <Author>Nick Athanas</Author>
  <AuthorID>XRABICUARW</AuthorID>
  <Content>song</Content>
  <Comments>ID by Vitor Piacentini, originally uploaded as Schistocichla rufifacies.bird-seen:noplayback-used:no</Comments>
  <Quality>2</Quality>
  <Year>BirdCLEF2014</Year>
  <BackgroundSpecies>Turdus albicollis,Campephilus rubricollis,Psittacara leucophthalmus,Pyrrhura amazonum</BackgroundSpecies>
  <Order>Passeriformes</Order>
  <Family>Thamnophilidae</Family>
  <Genus>Sclateria</Genus>
  <Species>naevia</Species>
  <Sub-species />
  <VernacularNames>Silvered Antbird</VernacularNames>
</Audio>
