<?xml version="1.0" encoding="UTF-8"?>
<Audio>
  <MediaId>7589</MediaId>
  <FileName>LIFECLEF2014_BIRDAMAZON_XC_WAV_RN7589.wav</FileName>
  <ClassId>dvcjbu</ClassId>
  <Date>2006-08-22</Date>
  <Time>22:00</Time>
  <Locality>Reserva Ecológica de Guapiaçu, RJ</Locality>
  <Latitude>-22.5001</Latitude>
  <Longitude>-42.7167</Longitude>
  <Elevation>40</Elevation>
  <Author>Frank Lambert</Author>
  <AuthorID>YTUXOCTUEM</AuthorID>
  <Content>song</Content>
  <Comments />
  <Quality>1</Quality>
  <Year>BirdCLEF2014</Year>
  <BackgroundSpecies />
  <Order>Strigiformes</Order>
  <Family>Strigidae</Family>
  <Genus>Pulsatrix</Genus>
  <Species>koeniswaldiana</Species>
  <Sub-species />
  <VernacularNames>Tawny-browed Owl</VernacularNames>
</Audio>
